svidreader/ImageReader.py
svidreader/__init__.py
svidreader/__main__.py
svidreader/analyze_image.py
svidreader/cameraprojection.py
svidreader/decord_video_wrapper.py
svidreader/dump_to_file.py
svidreader/effects.py
svidreader/filtergraph.py
svidreader/frame_iterator.py
svidreader/imagecache.py
svidreader/light_detector.py
svidreader/local_radial.py
svidreader/majorityvote.py
svidreader/mask_unfocused.py
svidreader/reader.py
svidreader/run_pipeline.py
svidreader/test_filtergraph.py
svidreader/test_filters.py
svidreader/test_zip_image_archives.py
svidreader/video_supplier.py
svidreader/videoscraper.py
svidreader/viewer.py
svidreader/filter/color_mapper.py
svidreader/filter/downsample_resolution.py
svidreader/filter/flow.py
svidreader/filter/map_coordinates.py
bbo_svidreader-0.8.1.dist-info/METADATA
bbo_svidreader-0.8.1.dist-info/WHEEL
bbo_svidreader-0.8.1.dist-info/licenses/LICENSE
bbo_svidreader-0.8.1.dist-info/RECORD
