Metadata-Version: 2.4
Name: bbo-svidreader
Version: 0.8.1
Summary: Video reader on top of imageio that allows to build custom filter-pipelines
Project-URL: Homepage, https://github.com/bbo-lab/videoreader
Author-email: "BBO-lab @ caesar" <paul.stahr@mpinb.mpg.de>
License: BSD-3-Clause
License-File: LICENSE
Classifier: License :: OSI Approved :: BSD License
Classifier: Programming Language :: Python :: 3.9
Classifier: Programming Language :: Python :: 3.10
Requires-Dist: av
Requires-Dist: bbo-calibcamlib
Requires-Dist: bbo-ccvtools
Requires-Dist: imageio
Requires-Dist: numpy
Requires-Dist: pandas
Requires-Dist: pyyaml
Requires-Dist: scipy
